[
	{"background": "Iowan.png", "labels": {"en": "Iowan", "cs": "Ajowan"}},
	{"background": "Anise whole organic.png", "labels": {"en": "Anise whole organic", "cs": "Anýz celý BIO"}},
	{"background": "Anise whole.png", "labels": {"en": "Anise whole", "cs": "Anýz celý"}},
	{"background": "Ground anise.png", "labels": {"en": "Ground anise", "cs": "Anýz mletý"}},
	{"background": "Star anise whole organic.png", "labels": {"en": "Star anise whole organic", "cs": "Badyán celý BIO"}},
	{"background": "Star anise whole selection.png", "labels": {"en": "Star anise whole selection", "cs": "Badyán celý výběrový"}},
	{"background": "Star anise whole.png", "labels": {"en": "Star anise whole", "cs": "Badyán celý"}},
	{"background": "Ground star anise.png", "labels": {"en": "Ground star anise", "cs": "Badyán mletý"}},
	{"background": "Organic basil.png", "labels": {"en": "Organic basil", "cs": "Bazalka BIO"}},
	{"background": "Basil.png", "labels": {"en": "Basil", "cs": "Bazalka"}},
	{"background": "Whole organic bay leaf.png", "labels": {"en": "Whole organic bay leaf", "cs": "Bobkový list celý BIO"}},
	{"background": "Whole bay leaf.png", "labels": {"en": "Whole bay leaf", "cs": "Bobkový list celý"}},
	{"background": "Ground bay leaf.png", "labels": {"en": "Ground bay leaf", "cs": "Bobkový list mletý"}},
	{"background": "Celery leaf.png", "labels": {"en": "Celery leaf", "cs": "Celer list"}},
	{"background": "Celery seed.png", "labels": {"en": "Celery seed", "cs": "Celer semeno"}},
	{"background": "Crushed Carolina Reaper Chili.png", "labels": {"en": "Crushed Carolina Reaper Chili", "cs": "Chilli Carolina Reaper drcené"}},
	{"background": "Whole Habanero Chilli.png", "labels": {"en": "Whole Habanero Chilli", "cs": "Chilli Habanero celé"}},
	{"background": "Crushed Habanero Chili.png", "labels": {"en": "Crushed Habanero Chili", "cs": "Chilli Habanero drcené"}},
	{"background": "Habanero chili ground.png", "labels": {"en": "Habanero chili ground", "cs": "Chilli Habanero mleté"}},
	{"background": "Smoked Jalapeño Chipotle Chili.png", "labels": {"en": "Smoked Jalapeño Chipotle Chili", "cs": "Chilli Jalapeño Chipotle kouřové"}},
	{"background": "Green ground Jalapeño chili.png", "labels": {"en": "Green ground Jalapeño chili", "cs": "Chilli Jalapeño zelené mleté"}},
	{"background": "Red ground Jalapeño chili.png", "labels": {"en": "Red ground Jalapeño chili", "cs": "Chilli Jalapeño červené mleté"}},
	{"background": "Kashmiri Chilli.png", "labels": {"en": "Kashmiri Chilli", "cs": "Chilli Kashmiri"}},
	{"background": "Chilli rings.png", "labels": {"en": "Chilli rings", "cs": "Chilli kroužky"}},
	{"background": "Chili ground BIO.png", "labels": {"en": "Chili ground BIO", "cs": "Chilli mleté BIO"}},
	{"background": "Chilli ground.png", "labels": {"en": "Chilli ground", "cs": "Chilli mleté"}},
	{"background": "Chilli Naga Bhut Jolokia.png", "labels": {"en": "Chilli Naga Bhut Jolokia", "cs": "Chilli Naga Bhut Jolokia"}},
	{"background": "Chili threads.png", "labels": {"en": "Chili threads", "cs": "Chilli nitě"}},
	{"background": "Whole chili peppers.png", "labels": {"en": "Whole chili peppers", "cs": "Chilli papričky celé"}},
	{"background": "Crushed chili peppers.png", "labels": {"en": "Crushed chili peppers", "cs": "Chilli papričky drcené"}},
	{"background": "Onion granulated.png", "labels": {"en": "Onion granulated", "cs": "Cibule granulovaná"}},
	{"background": "Onion grinds.png", "labels": {"en": "Onion grinds", "cs": "Cibule mletá"}},
	{"background": "Fried onions.png", "labels": {"en": "Fried onions", "cs": "Cibule smažená"}},
	{"background": "Organic smoked granulated onion.png", "labels": {"en": "Organic smoked granulated onion", "cs": "Cibule uzená granulovaná BIO"}},
	{"background": "Organic sliced ​​onion.png", "labels": {"en": "Organic sliced ​​onion", "cs": "Cibule řezaná BIO"}},
	{"background": "Chopped onion.png", "labels": {"en": "Chopped onion", "cs": "Cibule řezaná"}},
	{"background": "Crushed organic lemon peel.png", "labels": {"en": "Crushed organic lemon peel", "cs": "Citronová kůra drcená BIO"}},
	{"background": "Crushed lemon peel.png", "labels": {"en": "Crushed lemon peel", "cs": "Citronová kůra drcená"}},
	{"background": "Lemon peel is ground.png", "labels": {"en": "Lemon peel is ground", "cs": "Citronová kůra mletá"}},
	{"background": "BIO lemongrass.png", "labels": {"en": "BIO lemongrass", "cs": "Citronová tráva BIO"}},
	{"background": "Lemongrass ground.png", "labels": {"en": "Lemongrass ground", "cs": "Citronová tráva mletá"}},
	{"background": "Lemon grass.png", "labels": {"en": "Lemon grass", "cs": "Citronová tráva"}},
	{"background": "Tarragon.png", "labels": {"en": "Tarragon", "cs": "Estragon"}},
	{"background": "Whole organic fennel.png", "labels": {"en": "Whole organic fennel", "cs": "Fenykl celý BIO"}},
	{"background": "Whole fennel.png", "labels": {"en": "Whole fennel", "cs": "Fenykl celý"}},
	{"background": "Ground fennel.png", "labels": {"en": "Ground fennel", "cs": "Fenykl mletý"}},
	{"background": "Ground galangal root.png", "labels": {"en": "Ground galangal root", "cs": "Galgán kořen mletý"}},
	{"background": "Whole organic white mustard.png", "labels": {"en": "Whole organic white mustard", "cs": "Hořčice bílá celá BIO"}},
	{"background": "Whole white mustard.png", "labels": {"en": "Whole white mustard", "cs": "Hořčice bílá celá"}},
	{"background": "White ground mustard.png", "labels": {"en": "White ground mustard", "cs": "Hořčice bílá mletá"}},
	{"background": "Whole black mustard.png", "labels": {"en": "Whole black mustard", "cs": "Hořčice černá celá"}},
	{"background": "All organic cloves.png", "labels": {"en": "All organic cloves", "cs": "Hřebíček celý BIO"}},
	{"background": "Whole clove.png", "labels": {"en": "Whole clove", "cs": "Hřebíček celý"}},
	{"background": "Ground cloves.png", "labels": {"en": "Ground cloves", "cs": "Hřebíček mletý"}},
	{"background": "Whole juniper.png", "labels": {"en": "Whole juniper", "cs": "Jalovec celý"}},
	{"background": "Ground juniper.png", "labels": {"en": "Ground juniper", "cs": "Jalovec mletý"}},
	{"background": "Whole red juniper.png", "labels": {"en": "Whole red juniper", "cs": "Jalovec červený celý"}},
	{"background": "Crushed cayenne pepper.png", "labels": {"en": "Crushed cayenne pepper", "cs": "Kajenský pepř drcený"}},
	{"background": "Ground cayenne pepper.png", "labels": {"en": "Ground cayenne pepper", "cs": "Kajenský pepř mletý"}},
	{"background": "Whole cardamom.png", "labels": {"en": "Whole cardamom", "cs": "Kardamom celý"}},
	{"background": "Ground cardamom.png", "labels": {"en": "Ground cardamom", "cs": "Kardamom mletý"}},
	{"background": "Cardamom green beans.png", "labels": {"en": "Cardamom green beans", "cs": "Kardamom zelená zrna"}},
	{"background": "Black cardamom.png", "labels": {"en": "Black cardamom", "cs": "Kardamom černý"}},
	{"background": "Curry leaves.png", "labels": {"en": "Curry leaves", "cs": "Kari listy"}},
	{"background": "Carob BIO.png", "labels": {"en": "Carob BIO", "cs": "Karob BIO"}},
	{"background": "Chervil.png", "labels": {"en": "Chervil", "cs": "Kerblík"}},
	{"background": "Whole organic Czech cumin.png", "labels": {"en": "Whole organic Czech cumin", "cs": "Kmín český celý BIO"}},
	{"background": "Whole Czech cumin.png", "labels": {"en": "Whole Czech cumin", "cs": "Kmín český celý"}},
	{"background": "Crushed Czech cumin.png", "labels": {"en": "Crushed Czech cumin", "cs": "Kmín český drcený"}},
	{"background": "Ground Czech cumin.png", "labels": {"en": "Ground Czech cumin", "cs": "Kmín český mletý"}},
	{"background": "Dill fruit.png", "labels": {"en": "Dill fruit", "cs": "Kopr plod"}},
	{"background": "Dill.png", "labels": {"en": "Dill", "cs": "Kopr"}},
	{"background": "Whole organic coriander.png", "labels": {"en": "Whole organic coriander", "cs": "Koriandr celý BIO"}},
	{"background": "Whole cilantro.png", "labels": {"en": "Whole cilantro", "cs": "Koriandr celý"}},
	{"background": "Coriander leaf.png", "labels": {"en": "Coriander leaf", "cs": "Koriandr list"}},
	{"background": "Ground coriander.png", "labels": {"en": "Ground coriander", "cs": "Koriandr mletý"}},
	{"background": "Organic turmeric.png", "labels": {"en": "Organic turmeric", "cs": "Kurkuma BIO"}},
	{"background": "Crushed turmeric.png", "labels": {"en": "Crushed turmeric", "cs": "Kurkuma drcená"}},
	{"background": "Turmeric.png", "labels": {"en": "Turmeric", "cs": "Kurkuma"}},
	{"background": "Ground horseradish.png", "labels": {"en": "Ground horseradish", "cs": "Křen mletý"}},
	{"background": "Lovage.png", "labels": {"en": "Lovage", "cs": "Libeček"}},
	{"background": "Organic marjoram.png", "labels": {"en": "Organic marjoram", "cs": "Majoránka BIO"}},
	{"background": "Marjoram.png", "labels": {"en": "Marjoram", "cs": "Majoránka"}},
	{"background": "Crushed mandarin peel BIO.png", "labels": {"en": "Crushed mandarin peel BIO", "cs": "Mandarinková kůra drcená BIO"}},
	{"background": "Mango powder.png", "labels": {"en": "Mango powder", "cs": "Mangový prášek"}},
	{"background": "Bear garlic.png", "labels": {"en": "Bear garlic", "cs": "Medvědí česnek"}},
	{"background": "Whole mace flower.png", "labels": {"en": "Whole mace flower", "cs": "Muškátový květ celý"}},
	{"background": "Ground nutmeg flower.png", "labels": {"en": "Ground nutmeg flower", "cs": "Muškátový květ mletý"}},
	{"background": "Whole nutmeg.png", "labels": {"en": "Whole nutmeg", "cs": "Muškátový ořech celý"}},
	{"background": "Ground nutmeg.png", "labels": {"en": "Ground nutmeg", "cs": "Muškátový ořech mletý"}},
	{"background": "New spices whole.png", "labels": {"en": "New spices whole", "cs": "Nové koření celé"}},
	{"background": "Fresh ground spices.png", "labels": {"en": "Fresh ground spices", "cs": "Nové koření mleté"}},
	{"background": "Organic oregano.png", "labels": {"en": "Organic oregano", "cs": "Oregano BIO"}},
	{"background": "Oregano.png", "labels": {"en": "Oregano", "cs": "Oregano"}},
	{"background": "ORGANIC hot pepper.png", "labels": {"en": "ORGANIC hot pepper", "cs": "Paprika pálivá BIO"}},
	{"background": "Hot Hungarian paprika.png", "labels": {"en": "Hot Hungarian paprika", "cs": "Paprika pálivá maďarská"}},
	{"background": "Spanish hot pepper.png", "labels": {"en": "Spanish hot pepper", "cs": "Paprika pálivá španělská"}},
	{"background": "ORGANIC sweet pepper.png", "labels": {"en": "ORGANIC sweet pepper", "cs": "Paprika sladká BIO"}},
	{"background": "Sweet Hungarian paprika.png", "labels": {"en": "Sweet Hungarian paprika", "cs": "Paprika sladká maďarská"}},
	{"background": "Spanish sweet pepper.png", "labels": {"en": "Spanish sweet pepper", "cs": "Paprika sladká španělská"}},
	{"background": "Hot smoked paprika.png", "labels": {"en": "Hot smoked paprika", "cs": "Paprika uzená pálivá"}},
	{"background": "Sweet smoked paprika.png", "labels": {"en": "Sweet smoked paprika", "cs": "Paprika uzená sladká"}},
	{"background": "Pepper flakes green.png", "labels": {"en": "Pepper flakes green", "cs": "Paprika vločky zelená"}},
	{"background": "Red pepper flakes.png", "labels": {"en": "Red pepper flakes", "cs": "Paprika vločky červená"}},
	{"background": "Chive.png", "labels": {"en": "Chive", "cs": "Pažitka"}},
	{"background": "Bourbon pepper.png", "labels": {"en": "Bourbon pepper", "cs": "Pepř bourbonský"}},
	{"background": "Whole organic white pepper.png", "labels": {"en": "Whole organic white pepper", "cs": "Pepř bílý celý BIO"}},
	{"background": "Whole white pepper.png", "labels": {"en": "Whole white pepper", "cs": "Pepř bílý celý"}},
	{"background": "Ground white pepper.png", "labels": {"en": "Ground white pepper", "cs": "Pepř bílý mletý"}},
	{"background": "Ceylon black pepper whole.png", "labels": {"en": "Ceylon black pepper whole", "cs": "Pepř cejlonský černý celý"}},
	{"background": "Long pepper.png", "labels": {"en": "Long pepper", "cs": "Pepř dlouhý"}},
	{"background": "Grapefruit pepper.png", "labels": {"en": "Grapefruit pepper", "cs": "Pepř grapefruitový"}},
	{"background": "Guinea pepper - tomato seeds.png", "labels": {"en": "Guinea pepper - tomato seeds", "cs": "Pepř guinejský - rajská zrna"}},
	{"background": "Kampot long pepper.png", "labels": {"en": "Kampot long pepper", "cs": "Pepř kampotský dlouhý"}},
	{"background": "Fermented Kampot pepper.png", "labels": {"en": "Fermented Kampot pepper", "cs": "Pepř kampotský fermentovaný"}},
	{"background": "Kampot black pepper.png", "labels": {"en": "Kampot black pepper", "cs": "Pepř kampotský černý"}},
	{"background": "Kampot red pepper.png", "labels": {"en": "Kampot red pepper", "cs": "Pepř kampotský červený"}},
	{"background": "Cubeb pepper.png", "labels": {"en": "Cubeb pepper", "cs": "Pepř kubebový"}},
	{"background": "Whole pink (red) pepper.png", "labels": {"en": "Whole pink (red) pepper", "cs": "Pepř růžový (červený) celý"}},
	{"background": "Szechuan pepper whole.png", "labels": {"en": "Szechuan pepper whole", "cs": "Pepř sečuánský celý"}},
	{"background": "Szechuan ground pepper.png", "labels": {"en": "Szechuan ground pepper", "cs": "Pepř sečuánský mletý"}},
	{"background": "Szechuan pepper Timut whole BIO.png", "labels": {"en": "Szechuan pepper Timut whole BIO", "cs": "Pepř sečuánský Timut celý BIO"}},
	{"background": "Szechuan green pepper whole.png", "labels": {"en": "Szechuan green pepper whole", "cs": "Pepř sečuánský zelený celý"}},
	{"background": "Tasmanian pepper.png", "labels": {"en": "Tasmanian pepper", "cs": "Pepř tasmánský"}},
	{"background": "Tellicherry pepper.png", "labels": {"en": "Tellicherry pepper", "cs": "Pepř Tellicherry"}},
	{"background": "Whole green pepper.png", "labels": {"en": "Whole green pepper", "cs": "Pepř zelený celý"}},
	{"background": "Ground green pepper.png", "labels": {"en": "Ground green pepper", "cs": "Pepř zelený mletý"}},
	{"background": "Organic whole black pepper.png", "labels": {"en": "Organic whole black pepper", "cs": "Pepř černý celý BIO"}},
	{"background": "Whole black pepper.png", "labels": {"en": "Whole black pepper", "cs": "Pepř černý celý"}},
	{"background": "Crushed black pepper.png", "labels": {"en": "Crushed black pepper", "cs": "Pepř černý drcený"}},
	{"background": "Lampong black pepper.png", "labels": {"en": "Lampong black pepper", "cs": "Pepř černý Lampong"}},
	{"background": "Malabar black pepper.png", "labels": {"en": "Malabar black pepper", "cs": "Pepř černý Malabar"}},
	{"background": "BIO ground black pepper.png", "labels": {"en": "BIO ground black pepper", "cs": "Pepř černý mletý BIO"}},
	{"background": "Ground black pepper.png", "labels": {"en": "Ground black pepper", "cs": "Pepř černý mletý"}},
	{"background": "Parsley BIO.png", "labels": {"en": "Parsley BIO", "cs": "Petržel nať BIO"}},
	{"background": "Chop parsley.png", "labels": {"en": "Chop parsley", "cs": "Petržel nať"}},
	{"background": "ORGANIC crushed orange peel.png", "labels": {"en": "ORGANIC crushed orange peel", "cs": "Pomerančová kůra drcená BIO"}},
	{"background": "Orange peel ground.png", "labels": {"en": "Orange peel ground", "cs": "Pomerančová kůra mletá"}},
	{"background": "Fenugreek whole.png", "labels": {"en": "Fenugreek whole", "cs": "Pískavice celá"}},
	{"background": "Fenugreek leaves.png", "labels": {"en": "Fenugreek leaves", "cs": "Pískavice listy"}},
	{"background": "Fenugreek grinds.png", "labels": {"en": "Fenugreek grinds", "cs": "Pískavice mletá"}},
	{"background": "Blue ground fenugreek.png", "labels": {"en": "Blue ground fenugreek", "cs": "Pískavice modrá mletá"}},
	{"background": "Paradise apples.png", "labels": {"en": "Paradise apples", "cs": "Rajská jablíčka"}},
	{"background": "Ground rosemary.png", "labels": {"en": "Ground rosemary", "cs": "Rozmarýn mletý"}},
	{"background": "Rosemary.png", "labels": {"en": "Rosemary", "cs": "Rozmarýn"}},
	{"background": "Crushed sage.png", "labels": {"en": "Crushed sage", "cs": "Saturejka drcená"}},
	{"background": "Saturejka grinds.png", "labels": {"en": "Saturejka grinds", "cs": "Saturejka mletá"}},
	{"background": "Ceylon cinnamon whole BIO.png", "labels": {"en": "Ceylon cinnamon whole BIO", "cs": "Skořice cejlonská celá BIO"}},
	{"background": "Ceylon cinnamon whole.png", "labels": {"en": "Ceylon cinnamon whole", "cs": "Skořice cejlonská celá"}},
	{"background": "Ceylon cinnamon ground BIO.png", "labels": {"en": "Ceylon cinnamon ground BIO", "cs": "Skořice cejlonská mletá BIO"}},
	{"background": "Ground Ceylon cinnamon.png", "labels": {"en": "Ground Ceylon cinnamon", "cs": "Skořice cejlonská mletá"}},
	{"background": "Whole organic Indonesian cinnamon.png", "labels": {"en": "Whole organic Indonesian cinnamon", "cs": "Skořice indonéská celá BIO"}},
	{"background": "Whole Indonesian cinnamon.png", "labels": {"en": "Whole Indonesian cinnamon", "cs": "Skořice indonéská celá"}},
	{"background": "Organic ground Indonesian cinnamon.png", "labels": {"en": "Organic ground Indonesian cinnamon", "cs": "Skořice indonéská mletá BIO"}},
	{"background": "Ground Indonesian cinnamon.png", "labels": {"en": "Ground Indonesian cinnamon", "cs": "Skořice indonéská mletá"}},
	{"background": "Cinnamon flowers.png", "labels": {"en": "Cinnamon flowers", "cs": "Skořicové květy"}},
	{"background": "Sumah.png", "labels": {"en": "Sumah", "cs": "Sumah"}},
	{"background": "Nitrite salt without iodine.png", "labels": {"en": "Nitrite salt without iodine", "cs": "Sůl dusitanová bez jódu"}},
	{"background": "Nitrite salt with iodine.png", "labels": {"en": "Nitrite salt with iodine", "cs": "Sůl dusitanová s jódem"}},
	{"background": "Salt Fleur de Sel natural.png", "labels": {"en": "Salt Fleur de Sel natural", "cs": "Sůl Fleur de Sel natural"}},
	{"background": "Fleur de Sel flaky salt.png", "labels": {"en": "Fleur de Sel flaky salt", "cs": "Sůl Fleur de Sel vločková"}},
	{"background": "Coarse Himalayan salt.png", "labels": {"en": "Coarse Himalayan salt", "cs": "Sůl himalájská hrubá"}},
	{"background": "Himalayan salt fine pink.png", "labels": {"en": "Himalayan salt fine pink", "cs": "Sůl himalájská jemná růžová"}},
	{"background": "Coarse-grained salt.png", "labels": {"en": "Coarse-grained salt", "cs": "Sůl hrubozrnná"}},
	{"background": "Coarse sea salt.png", "labels": {"en": "Coarse sea salt", "cs": "Sůl mořská hrubá"}},
	{"background": "Fine sea salt.png", "labels": {"en": "Fine sea salt", "cs": "Sůl mořská jemná"}},
	{"background": "Maldon sea salt.png", "labels": {"en": "Maldon sea salt", "cs": "Sůl mořská maldonská"}},
	{"background": "Smoked sea salt.png", "labels": {"en": "Smoked sea salt", "cs": "Sůl mořská uzená"}},
	{"background": "Persian blue salt.png", "labels": {"en": "Persian blue salt", "cs": "Sůl perská modrá"}},
	{"background": "Black salt.png", "labels": {"en": "Black salt", "cs": "Sůl černá"}},
	{"background": "Tonka beans.png", "labels": {"en": "Tonka beans", "cs": "Tonka fazole"}},
	{"background": "Organic thyme.png", "labels": {"en": "Organic thyme", "cs": "Tymián BIO"}},
	{"background": "Thyme.png", "labels": {"en": "Thyme", "cs": "Tymián"}},
	{"background": "Vanilla Bean Bourbon Madagascar.png", "labels": {"en": "Vanilla Bean Bourbon Madagascar", "cs": "Vanilka lusk Bourbon Madagaskar"}},
	{"background": "Vanilla Bean Bourbon Uganda.png", "labels": {"en": "Vanilla Bean Bourbon Uganda", "cs": "Vanilka lusk Bourbon Uganda"}},
	{"background": "Vanilla ground Madagascar.png", "labels": {"en": "Vanilla ground Madagascar", "cs": "Vanilka mletá Madagaskar"}},
	{"background": "Vanilla grinds Uganda.png", "labels": {"en": "Vanilla grinds Uganda", "cs": "Vanilka mletá Uganda"}},
	{"background": "BIO ground ginger.png", "labels": {"en": "BIO ground ginger", "cs": "Zázvor mletý BIO"}},
	{"background": "Ground ginger.png", "labels": {"en": "Ground ginger", "cs": "Zázvor mletý"}},
	{"background": "Ginger sliced.png", "labels": {"en": "Ginger sliced", "cs": "Zázvor řezaný"}},
	{"background": "Nigella BIO.png", "labels": {"en": "Nigella BIO", "cs": "Černucha BIO"}},
	{"background": "Nigella.png", "labels": {"en": "Nigella", "cs": "Černucha"}},
	{"background": "Holy shit.png", "labels": {"en": "Holy shit", "cs": "Čertovo lejno celé"}},
	{"background": "Minced devil shit.png", "labels": {"en": "Minced devil shit", "cs": "Čertovo lejno mleté"}},
	{"background": "Organic granulated garlic.png", "labels": {"en": "Organic granulated garlic", "cs": "Česnek granulovaný BIO"}},
	{"background": "Granulated garlic.png", "labels": {"en": "Granulated garlic", "cs": "Česnek granulovaný"}},
	{"background": "Organic minced garlic.png", "labels": {"en": "Organic minced garlic", "cs": "Česnek mletý BIO"}},
	{"background": "Minced garlic.png", "labels": {"en": "Minced garlic", "cs": "Česnek mletý"}},
	{"background": "Garlic slices.png", "labels": {"en": "Garlic slices", "cs": "Česnek plátky"}},
	{"background": "Roman cumin whole.png", "labels": {"en": "Roman cumin whole", "cs": "Římský kmín celý"}},
	{"background": "Roman cumin ground.png", "labels": {"en": "Roman cumin ground", "cs": "Římský kmín mletý"}},
	{"background": "Saffron.png", "labels": {"en": "Saffron", "cs": "Šafrán"}},
	{"background": "Sage.png", "labels": {"en": "Sage", "cs": "Šalvěj"}}
]